arcor2_ur/VERSION
arcor2_ur/__init__.py
arcor2_ur/exceptions.py
arcor2_ur/py.typed
arcor2_ur/data/moveit.yaml
arcor2_ur/scripts/__init__.py
arcor2_ur/scripts/ur.py
arcor2_ur-1.1.0.dist-info/METADATA
arcor2_ur-1.1.0.dist-info/WHEEL
arcor2_ur-1.1.0.dist-info/entry_points.txt
arcor2_ur-1.1.0.dist-info/namespace_packages.txt
arcor2_ur-1.1.0.dist-info/top_level.txt
arcor2_ur-1.1.0.dist-info/RECORD
